prio_merge/__init__.py
prio_merge/prio_merge.py
prio_merge-0.0.2.dist-info/LICENSE
prio_merge-0.0.2.dist-info/METADATA
prio_merge-0.0.2.dist-info/WHEEL
prio_merge-0.0.2.dist-info/top_level.txt
prio_merge-0.0.2.dist-info/RECORD
