Metadata-Version: 2.1
Name: prio-merge
Version: 0.0.2
Summary: Merge nested dicts according to a few specific rules
Home-page: https://github.com/ztime/prio-merge
Author: Jonas Wedin
Author-email: jonas@lechuck.se
License: UNKNOWN
Platform: UNKNOWN
Classifier: Programming Language :: Python :: 3
Classifier: License :: OSI Approved :: MIT License
Classifier: Operating System :: OS Independent
Requires-Python: >=3.6
